enhanceml/__init__.py
enhanceml/enhancer.py
enhanceml-0.0.1.dist-info/LICENSE
enhanceml-0.0.1.dist-info/METADATA
enhanceml-0.0.1.dist-info/WHEEL
enhanceml-0.0.1.dist-info/top_level.txt
enhanceml-0.0.1.dist-info/RECORD
