Metadata-Version: 2.1
Name: enhanceml
Version: 0.0.1
Summary: An ML enhancement package to improve outcomes
Home-page: https://github.com/sumitc29/enhanceml.git
Author: Sumit Chandak
Author-email: chandaksumit29@gmail.com
License: MIT
Platform: UNKNOWN
Classifier: Programming Language :: Python :: 3
Classifier: License :: OSI Approved :: MIT License
Classifier: Operating System :: OS Independent
